Workbook

Sheet Léeme
A1: Vento — Modelo financiero y plan de inversión
A2: Versión 1 · octubre 2026 · valores en pesos colombianos (COP) salvo que diga US$
A4: Cómo usarlo
A5: Celdas en AZUL | B5: Son supuestos que puedes cambiar (precios, clientes nuevos, salarios…). Todo lo demás se recalcula solo.
A6: Celdas con fondo AMARILLO | B6: Supuestos clave: revísalos primero con datos reales de tus pilotos.
A7: Texto VERDE | B7: Trae un valor de otra hoja.
A9: Hojas
A10: Supuestos | B10: Tasa de cambio, mezcla de planes, abandono, costos por cliente y crecimiento en 3 escenarios.
A11: Competencia | B11: Precios públicos de otras soluciones en Colombia, con fuente.
A12: Precios | B12: Tres formas de cobrar Vento (opciones A, B y C) en COP y US$.
A13: Presupuesto | B13: Equipo y gastos mensuales, desde qué mes empieza cada uno, y gastos de arranque.
A14: Proyección | B14: 36 meses por escenario: clientes, ingresos, costos, resultado y caja.
A15: Resumen | B15: Lo que se muestra a inversionistas: ingresos por año, punto de equilibrio y cuánta plata se necesita.
A16: Unidad económica | B16: Cuánto vale un cliente (LTV), cuánto cuesta conseguirlo (CAC) y en cuánto se recupera.
A17: Uso de fondos | B17: Tres tamaños de ronda y en qué se gasta cada peso.
A19: Importante | B19: Las proyecciones son ESTIMACIONES con supuestos, no resultados. Los salarios y costos son referencias para planear: confírmalos con cotizaciones reales antes de presentarlos como definitivos.

Sheet Resumen
A1: Resumen para inversionistas
A2: Se calcula solo desde la Proyección. COP salvo que diga US$.
A4: Indicador | B4: Conservador | C4: Base | D4: Optimista
A5: Clientes activos al final del año 1 | B5: =INDEX(Proyección!$C$10:$AL$10,12) | C5: =INDEX(Proyección!$C$24:$AL$24,12) | D5: =INDEX(Proyección!$C$38:$AL$38,12)
A6: Clientes activos al final del año 2 | B6: =INDEX(Proyección!$C$10:$AL$10,24) | C6: =INDEX(Proyección!$C$24:$AL$24,24) | D6: =INDEX(Proyección!$C$38:$AL$38,24)
A7: Clientes activos al final del año 3 | B7: =INDEX(Proyección!$C$10:$AL$10,36) | C7: =INDEX(Proyección!$C$24:$AL$24,36) | D7: =INDEX(Proyección!$C$38:$AL$38,36)
A8: Ingresos año 1 | B8: =SUMPRODUCT((Proyección!$C$5:$AL$5=1)*Proyección!$C$12:$AL$12) | C8: =SUMPRODUCT((Proyección!$C$5:$AL$5=1)*Proyección!$C$26:$AL$26) | D8: =SUMPRODUCT((Proyección!$C$5:$AL$5=1)*Proyección!$C$40:$AL$40)
A9: Ingresos año 2 | B9: =SUMPRODUCT((Proyección!$C$5:$AL$5=2)*Proyección!$C$12:$AL$12) | C9: =SUMPRODUCT((Proyección!$C$5:$AL$5=2)*Proyección!$C$26:$AL$26) | D9: =SUMPRODUCT((Proyección!$C$5:$AL$5=2)*Proyección!$C$40:$AL$40)
A10: Ingresos año 3 | B10: =SUMPRODUCT((Proyección!$C$5:$AL$5=3)*Proyección!$C$12:$AL$12) | C10: =SUMPRODUCT((Proyección!$C$5:$AL$5=3)*Proyección!$C$26:$AL$26) | D10: =SUMPRODUCT((Proyección!$C$5:$AL$5=3)*Proyección!$C$40:$AL$40)
A11: Ingresos año 3 en US$ | B11: =SUMPRODUCT((Proyección!$C$5:$AL$5=3)*Proyección!$C$12:$AL$12)/Supuestos!$C$5 | C11: =SUMPRODUCT((Proyección!$C$5:$AL$5=3)*Proyección!$C$26:$AL$26)/Supuestos!$C$5 | D11: =SUMPRODUCT((Proyección!$C$5:$AL$5=3)*Proyección!$C$40:$AL$40)/Supuestos!$C$5
A12: Ingreso recurrente anual al mes 36 (ARR) | B12: =INDEX(Proyección!$C$12:$AL$12,36)*12 | C12: =INDEX(Proyección!$C$26:$AL$26,36)*12 | D12: =INDEX(Proyección!$C$40:$AL$40,36)*12
A13: ARR al mes 36 en US$ | B13: =INDEX(Proyección!$C$12:$AL$12,36)*12/Supuestos!$C$5 | C13: =INDEX(Proyección!$C$26:$AL$26,36)*12/Supuestos!$C$5 | D13: =INDEX(Proyección!$C$40:$AL$40,36)*12/Supuestos!$C$5
A14: Resultado operativo año 3 (EBITDA) | B14: =SUMPRODUCT((Proyección!$C$5:$AL$5=3)*Proyección!$C$16:$AL$16) | C14: =SUMPRODUCT((Proyección!$C$5:$AL$5=3)*Proyección!$C$30:$AL$30) | D14: =SUMPRODUCT((Proyección!$C$5:$AL$5=3)*Proyección!$C$44:$AL$44)
A15: Mes del punto de equilibrio | B15: =IFERROR(MATCH(1,Proyección!$C$18:$AL$18,0),"después del mes 36") | C15: =IFERROR(MATCH(1,Proyección!$C$32:$AL$32,0),"después del mes 36") | D15: =IFERROR(MATCH(1,Proyección!$C$46:$AL$46,0),"después del mes 36")
A16: Plata necesaria para llegar ahí (caja mínima) | B16: =MAX(0,-MIN(Proyección!$C$17:$AL$17)) | C16: =MAX(0,-MIN(Proyección!$C$31:$AL$31)) | D16: =MAX(0,-MIN(Proyección!$C$45:$AL$45))
A17: Plata necesaria en US$ | B17: =MAX(0,-MIN(Proyección!$C$17:$AL$17))/Supuestos!$C$5 | C17: =MAX(0,-MIN(Proyección!$C$31:$AL$31))/Supuestos!$C$5 | D17: =MAX(0,-MIN(Proyección!$C$45:$AL$45))/Supuestos!$C$5
A19: Participación del mercado al mes 36 (sobre 2,3 millones de micronegocios, DANE 2024) | B19: =INDEX(Proyección!$C$10:$AL$10,36)/2321469 | C19: =INDEX(Proyección!$C$24:$AL$24,36)/2321469 | D19: =INDEX(Proyección!$C$38:$AL$38,36)/2321469
A21: Lectura: incluso el escenario optimista llega a menos del 1 % de los micronegocios de las 24 ciudades principales.

Sheet Supuestos
A1: Supuestos
A2: Cambia las celdas azules; el resto del libro se actualiza
A4: Supuesto | B4: Unidad | C4: Conservador | D4: Base | E4: Optimista | F4: Nota / fuente
A5: Tasa de cambio (TRM) | B5: COP por US$ | C5: 3313 | D5: =$C$5 | E5: =$C$5 | F5: TRM del 1 de octubre de 2026: $3.312,84 (dolar-colombia.com).
A6: Clientes nuevos el mes 1 | B6: negocios | C6: 10 | D6: 20 | E6: 40 | F6: Estimación. Reemplazar con el resultado de los pilotos.
A7: Crecimiento mensual de clientes nuevos | B7: % mensual | C7: 0.08 | D7: 0.1 | E7: 0.12 | F7: Estimación: ventas de campo + referidos + Play Store.
A8: Abandono mensual (churn) | B8: % de activos | C8: 0.05 | D8: 0.04 | E8: 0.03 | F8: Estimación habitual para software de pequeños negocios; medir en pilotos.
A9: Ingreso promedio por cliente (ARPU) | B9: COP / mes | C9: =Precios!$I$13 | D9: =Precios!$I$13 | E9: =Precios!$I$13 | F9: Calculado con los precios y la mezcla de la opción B (hoja Precios).
A10: Costo variable por cliente | B10: COP / mes | C10: 6000 | D10: =$C$10 | E10: =$C$10 | F10: Estimado: servidor, IA, mensajes y soporte por cliente activo.
A11: Comisión de cobro de la suscripción | B11: % del ingreso | C11: 0.03 | D11: =$C$11 | E11: =$C$11 | F11: Estimado si el cliente paga con pasarela o tienda de apps.
A12: Costo de conseguir un cliente (CAC) | B12: COP | C12: 250000 | D12: =$C$12 | E12: =$C$12 | F12: Estimado: un vendedor de campo cuesta ~$4,3 M/mes con prestaciones y cierra ~20 negocios al mes, más material y pauta. Medir en pilotos.
A13: Factor prestacional (salarios) | B13: veces el salario | C13: 1.52 | D13: =$C$13 | E13: =$C$13 | F13: Referencia habitual en Colombia para un empleado con todas las prestaciones; confirmar con el contador.

Sheet Competencia
A1: Competencia en Colombia — precios públicos
A2: Solo datos encontrados en fuentes públicas (octubre 2026). Verifica en el sitio de cada empresa antes de citarlos.
A4: Solución | B4: Qué es | C4: Precio publicado | D4: COP / mes (aprox.) | E4: US$ / mes | F4: Fuente
A5: Alegra (plan Pyme) | B5: Contabilidad + factura electrónica + POS | C5: $163.900 COP / mes | D5: 163900 | E5: =D5/Supuestos!$C$5 | F5: https://blog.alegra.com/colombia/alegra-vs-siigo-colombia/
A6: Siigo Nube (Emprendedor) | B6: Contabilidad y facturación | C6: $191.327 COP / mes | D6: 191327 | E6: =D6/Supuestos!$C$5 | F6: https://blog.alegra.com/colombia/alegra-vs-siigo-colombia/
A7: Siigo POS Gastrobar | B7: POS para restaurantes y bares | C7: desde $124.992 COP / mes | D7: 124992 | E7: =D7/Supuestos!$C$5 | F7: https://www.descubre.vc/noticia/siigo-lanza-pos-gastrobar-para-restaurantes-y-bares-en-colombia-2025-08-19
A8: Fudo (planes internacionales) | B8: Software para restaurantes | C8: US$35 – US$45 / mes | D8: =40*Supuestos!$C$5 | E8: =D8/Supuestos!$C$5 | F8: https://www.capterra.co.uk/software/1023879/fudo
A9: Treinta | B9: App para micronegocios (ventas, fiados, inventario) | C9: Gratis (funciones básicas) | D9: 0 | E9: =D9/Supuestos!$C$5 | F9: https://www.larepublica.co/finanzas/queremos-ser-la-super-app-de-referencia-para-los-micronegocios-de-america-latina-3404790
A10: Bold (datáfono) | B10: Cobros con tarjeta y QR | C10: 2,99 % por transacción | D10: no aplica (cobra por venta) | F10: https://www.larepublica.co/finanzas/la-fintech-bold-llego-a-230-000-comercios-y-anuncio-su-nuevo-proyecto-bold-smart-3430336
A12: Promedio de las soluciones pagas con precio mensual | D12: =AVERAGE(D5:D8) | E12: =D12/Supuestos!$C$5
A13: Fudo: se usa el punto medio (US$40) convertido con la TRM.

Sheet Precios
A1: Cómo cobrar Vento — tres opciones
A2: Los precios son propuestas (azul). La opción B es la recomendada y alimenta el modelo.
A4: Opción | B4: Plan | C4: Para quién | D4: Incluye | E4: Precio COP / mes | F4: US$ / mes | G4: Precio anual (2 meses gratis) | H4: Mezcla esperada | I4: Aporte al ARPU
A5: A · Gratis + Pro | B5: Gratis | C5: Tiendas que empiezan | D5: Ventas, fiados, 1 celular, sin IA ni QR | E5: 0 | F5: =E5/Supuestos!$C$5 | G5: =E5*10
A6: A · Gratis + Pro | B6: Pro | C6: Negocios que crecen | D6: Todo: voz, IA, QR, música, pagos verificados | E6: 59900 | F6: =E6/Supuestos!$C$5 | G6: =E6*10
A7: B · Por tamaño (recomendada) | B7: Tienda | C7: Tienda de barrio, 1 caja | D7: 1 celular, voz, fiados, inventario, pagos verificados | E7: 39900 | F7: =E7/Supuestos!$C$5 | G7: =E7*10 | H7: 0.4 | I7: =E7*H7
A8: B · Por tamaño (recomendada) | B8: Restobar | C8: Bares, restaurantes, cafés | D8: Hasta 5 equipos, mesas, QR, música en el TV, Vento IA | E8: 79900 | F8: =E8/Supuestos!$C$5 | G8: =E8*10 | H8: 0.45 | I8: =E8*H8
A9: B · Por tamaño (recomendada) | B9: Plus | C9: Varios locales o equipos grandes | D9: Equipos ilimitados, varias sedes, soporte prioritario | E9: 149900 | F9: =E9/Supuestos!$C$5 | G9: =E9*10 | H9: 0.15 | I9: =E9*H9
A10: C · De por vida | B10: Licencia única | C10: Dueños que prefieren comprar | D10: Pago único + mantenimiento mensual de nube e IA | E10: 990000 | F10: =E10/Supuestos!$C$5 | G10: pago único
A11: C · De por vida | B11: Mantenimiento | C11: Quien compró la licencia | D11: Nube, IA, actualizaciones y soporte | E11: 19900 | F11: =E11/Supuestos!$C$5 | G11: =E11*10
A12: Revisión: la mezcla de la opción B debe sumar 100 % | H12: =SUM(H7:H9)
A13: ARPU de la opción B (ingreso promedio por cliente al mes) | I13: =SUM(I7:I9)
A14: Comparado con el promedio de la competencia paga | I14: =IFERROR(I13/Competencia!D12,0)
A15: Lectura: Vento cuesta menos que las soluciones de contabilidad/POS y no cobra comisión por venta como un datáfono.

Sheet Presupuesto
A1: Presupuesto — equipo y gastos
A2: Valores de referencia para planear (azul). Desde el mes indicado el gasto entra a la proyección.
A4: Concepto | B4: Tipo | C4: Valor mensual COP | D4: Desde el mes | E4: Costo mensual total COP | F4: US$ / mes | G4: Nota
A5: Fundador — producto y tecnología | B5: Salario | C5: 6000000 | D5: 1 | E5: =IF(B5="Salario",C5*Supuestos!$C$13,C5) | F5: =E5/Supuestos!$C$5 | G5: Hoy trabajan 2 fundadores (padre e hijo); salario a partir de la inversión.
A6: Cofundador — operación y relación con negocios | B6: Salario | C6: 5000000 | D6: 1 | E6: =IF(B6="Salario",C6*Supuestos!$C$13,C6) | F6: =E6/Supuestos!$C$5 | G6: Confirmar el rol exacto de cada fundador.
A7: Desarrollador(a) full-stack | B7: Salario | C7: 7000000 | D7: 2 | E7: =IF(B7="Salario",C7*Supuestos!$C$13,C7) | F7: =E7/Supuestos!$C$5 | G7: Separar index.html en módulos, Play Store, nube.
A8: Vendedor(a) de campo 1 | B8: Salario | C8: 2800000 | D8: 2 | E8: =IF(B8="Salario",C8*Supuestos!$C$13,C8) | F8: =E8/Supuestos!$C$5 | G8: Visitas a bares, restaurantes y tiendas.
A9: Marketing digital y contenido | B9: Gasto | C9: 3000000 | D9: 2 | E9: =IF(B9="Salario",C9*Supuestos!$C$13,C9) | F9: =E9/Supuestos!$C$5 | G9: Pauta, video, TikTok/Instagram, ficha de Play Store.
A10: Diseño UX (medio tiempo) | B10: Salario | C10: 3000000 | D10: 3 | E10: =IF(B10="Salario",C10*Supuestos!$C$13,C10) | F10: =E10/Supuestos!$C$5 | G10: Primer uso, modo básico, ficha de Play.
A11: Desarrollador(a) Android / QA | B11: Salario | C11: 6000000 | D11: 4 | E11: =IF(B11="Salario",C11*Supuestos!$C$13,C11) | F11: =E11/Supuestos!$C$5 | G11: App nativa, pruebas en celulares reales.
A12: Soporte al cliente | B12: Salario | C12: 2500000 | D12: 4 | E12: =IF(B12="Salario",C12*Supuestos!$C$13,C12) | F12: =E12/Supuestos!$C$5 | G12: WhatsApp, capacitación, instalación.
A13: Vendedor(a) de campo 2 | B13: Salario | C13: 2800000 | D13: 6 | E13: =IF(B13="Salario",C13*Supuestos!$C$13,C13) | F13: =E13/Supuestos!$C$5 | G13: Segunda ciudad.
A14: Infraestructura y herramientas | B14: Gasto | C14: 600000 | D14: 1 | E14: =IF(B14="Salario",C14*Supuestos!$C$13,C14) | F14: =E14/Supuestos!$C$5 | G14: Servidor, dominio, correo, herramientas de desarrollo.
A15: Contador y asesoría legal | B15: Gasto | C15: 1500000 | D15: 1 | E15: =IF(B15="Salario",C15*Supuestos!$C$13,C15) | F15: =E15/Supuestos!$C$5 | G15: Contabilidad, habeas data, contratos.
A16: Oficina / coworking | B16: Gasto | C16: 1500000 | D16: 3 | E16: =IF(B16="Salario",C16*Supuestos!$C$13,C16) | F16: =E16/Supuestos!$C$5 | G16: Opcional.
A17: Gasto mensual con todo el equipo | E17: =SUM(E5:E16) | F17: =E17/Supuestos!$C$5
A19: Gastos de arranque (una sola vez)
A20: Concepto | C20: Valor COP | F20: US$ | G20: Nota
A21: Cuenta de desarrollador de Google Play | C21: =25*Supuestos!$C$5 | F21: =C21/Supuestos!$C$5 | G21: US$25, pago único (Google).
A22: Constitución de la empresa (SAS) y registros | C22: 1000000 | F22: =C22/Supuestos!$C$5 | G22: Estimado: confirmar en la Cámara de Comercio.
A23: Registro de la marca «Vento» (SIC) | C23: 1500000 | F23: =C23/Supuestos!$C$5 | G23: Estimado: confirmar tarifa vigente de la SIC y búsqueda de antecedentes.
A24: Política de privacidad y términos (abogado) | C24: 2000000 | F24: =C24/Supuestos!$C$5 | G24: Estimado.
A25: Integración de factura electrónica DIAN (proveedor) | C25: 5000000 | F25: =C25/Supuestos!$C$5 | G25: Estimado: depende del proveedor tecnológico autorizado.
A26: Celulares y tabletas de prueba | C26: 4000000 | F26: =C26/Supuestos!$C$5 | G26: Varias marcas y gamas.
A27: Marca, video y ficha de la Play Store | C27: 2000000 | F27: =C27/Supuestos!$C$5 | G27: Estimado.
A28: Total gastos de arranque | C28: =SUM(C21:C27) | F28: =C28/Supuestos!$C$5

Sheet Proyección
A1: Proyección a 36 meses por escenario
A2: COP. Clientes y ingresos con los supuestos de cada escenario; gastos fijos según el Presupuesto.
A4: Mes | C4: 1 | D4: 2 | E4: 3 | F4: 4 | G4: 5 | H4: 6 | I4: 7 | J4: 8 | K4: 9 | L4: 10 | M4: 11 | N4: 12 | O4: 13 | P4: 14 | Q4: 15 | R4: 16 | S4: 17 | T4: 18 | U4: 19 | V4: 20 | W4: 21 | X4: 22 | Y4: 23 | Z4: 24 | AA4: 25 | AB4: 26 | AC4: 27 | AD4: 28 | AE4: 29 | AF4: 30 | AG4: 31 | AH4: 32 | AI4: 33 | AJ4: 34 | AK4: 35 | AL4: 36
A5: Año | C5: =ROUNDUP(C4/12,0) | D5: =ROUNDUP(D4/12,0) | E5: =ROUNDUP(E4/12,0) | F5: =ROUNDUP(F4/12,0) | G5: =ROUNDUP(G4/12,0) | H5: =ROUNDUP(H4/12,0) | I5: =ROUNDUP(I4/12,0) | J5: =ROUNDUP(J4/12,0) | ... AL5: =ROUNDUP(AL4/12,0)
A7: Escenario Conservador
A8: Clientes nuevos | C8: =Supuestos!$C$6 | D8: =C8*(1+Supuestos!$C$7) | E8: =D8*(1+Supuestos!$C$7) | F8: =E8*(1+Supuestos!$C$7) | G8: =F8*(1+Supuestos!$C$7) | H8: =G8*(1+Supuestos!$C$7) | I8: =H8*(1+Supuestos!$C$7) | J8: =I8*(1+Supuestos!$C$7) | K8: =J8*(1+Supuestos!$C$7) | ... AL8: =AK8*(1+Supuestos!$C$7)
A9: Clientes que se van | C9: =0 | D9: =C10*Supuestos!$C$8 | E9: =D10*Supuestos!$C$8 | F9: =E10*Supuestos!$C$8 | G9: =F10*Supuestos!$C$8 | H9: =G10*Supuestos!$C$8 | I9: =H10*Supuestos!$C$8 | J9: =I10*Supuestos!$C$8 | K9: =J10*Supuestos!$C$8 | ... AL9: =AK10*Supuestos!$C$8
A10: Clientes activos | C10: =C8 | D10: =C10+D8-D9 | E10: =D10+E8-E9 | F10: =E10+F8-F9 | G10: =F10+G8-G9 | H10: =G10+H8-H9 | I10: =H10+I8-I9 | J10: =I10+J8-J9 | K10: =J10+K8-K9 | ... AL10: =AK10+AL8-AL9
A11: Ingreso promedio por cliente (ARPU) | C11: =Supuestos!$C$9 | D11: =Supuestos!$C$9 | E11: =Supuestos!$C$9 | F11: =Supuestos!$C$9 | G11: =Supuestos!$C$9 | H11: =Supuestos!$C$9 | I11: =Supuestos!$C$9 | J11: =Supuestos!$C$9 | ... AL11: =Supuestos!$C$9
A12: Ingresos del mes | C12: =C10*C11 | D12: =D10*D11 | E12: =E10*E11 | F12: =F10*F11 | G12: =G10*G11 | H12: =H10*H11 | I12: =I10*I11 | J12: =J10*J11 | ... AL12: =AL10*AL11
A13: Costos variables | C13: =C10*Supuestos!$C$10+C12*Supuestos!$C$11 | D13: =D10*Supuestos!$C$10+D12*Supuestos!$C$11 | E13: =E10*Supuestos!$C$10+E12*Supuestos!$C$11 | F13: =F10*Supuestos!$C$10+F12*Supuestos!$C$11 | G13: =G10*Supuestos!$C$10+G12*Supuestos!$C$11 | H13: =H10*Supuestos!$C$10+H12*Supuestos!$C$11 | I13: =I10*Supuestos!$C$10+I12*Supuestos!$C$11 | J13: =J10*Supuestos!$C$10+J12*Supuestos!$C$11 | ... AL13: =AL10*Supuestos!$C$10+AL12*Supuestos!$C$11
A14: Costo de conseguir clientes | C14: =C8*Supuestos!$C$12 | D14: =D8*Supuestos!$C$12 | E14: =E8*Supuestos!$C$12 | F14: =F8*Supuestos!$C$12 | G14: =G8*Supuestos!$C$12 | H14: =H8*Supuestos!$C$12 | I14: =I8*Supuestos!$C$12 | J14: =J8*Supuestos!$C$12 | ... AL14: =AL8*Supuestos!$C$12
A15: Gastos fijos (equipo y operación) | C15: =SUMPRODUCT((Presupuesto!$D$5:$D$16<=C$4)*Presupuesto!$E$5:$E$16) | D15: =SUMPRODUCT((Presupuesto!$D$5:$D$16<=D$4)*Presupuesto!$E$5:$E$16) | E15: =SUMPRODUCT((Presupuesto!$D$5:$D$16<=E$4)*Presupuesto!$E$5:$E$16) | F15: =SUMPRODUCT((Presupuesto!$D$5:$D$16<=F$4)*Presupuesto!$E$5:$E$16) | G15: =SUMPRODUCT((Presupuesto!$D$5:$D$16<=G$4)*Presupuesto!$E$5:$E$16) | H15: =SUMPRODUCT((Presupuesto!$D$5:$D$16<=H$4)*Presupuesto!$E$5:$E$16) | I15: =SUMPRODUCT((Presupuesto!$D$5:$D$16<=I$4)*Presupuesto!$E$5:$E$16) | J15: =SUMPRODUCT((Presupuesto!$D$5:$D$16<=J$4)*Presupuesto!$E$5:$E$16) | ... AL15: =SUMPRODUCT((Presupuesto!$D$5:$D$16<=AL$4)*Presupuesto!$E$5:$E$16)
A16: Resultado operativo (EBITDA) | C16: =C12-C13-C14-C15 | D16: =D12-D13-D14-D15 | E16: =E12-E13-E14-E15 | F16: =F12-F13-F14-F15 | G16: =G12-G13-G14-G15 | H16: =H12-H13-H14-H15 | I16: =I12-I13-I14-I15 | J16: =J12-J13-J14-J15 | ... AL16: =AL12-AL13-AL14-AL15
A17: Caja acumulada (sin inversión) | C17: =C16-Presupuesto!$C$28 | D17: =C17+D16 | E17: =D17+E16 | F17: =E17+F16 | G17: =F17+G16 | H17: =G17+H16 | I17: =H17+I16 | J17: =I17+J16 | K17: =J17+K16 | ... AL17: =AK17+AL16
A18: ¿Mes con resultado positivo? (1 = sí) | C18: =IF(C16>0,1,0) | D18: =IF(D16>0,1,0) | E18: =IF(E16>0,1,0) | F18: =IF(F16>0,1,0) | G18: =IF(G16>0,1,0) | H18: =IF(H16>0,1,0) | I18: =IF(I16>0,1,0) | J18: =IF(J16>0,1,0) | ... AL18: =IF(AL16>0,1,0)
A21: Escenario Base
A22: Clientes nuevos | C22: =Supuestos!$D$6 | D22: =C22*(1+Supuestos!$D$7) | E22: =D22*(1+Supuestos!$D$7) | F22: =E22*(1+Supuestos!$D$7) | G22: =F22*(1+Supuestos!$D$7) | H22: =G22*(1+Supuestos!$D$7) | I22: =H22*(1+Supuestos!$D$7) | J22: =I22*(1+Supuestos!$D$7) | K22: =J22*(1+Supuestos!$D$7) | ... AL22: =AK22*(1+Supuestos!$D$7)
A23: Clientes que se van | C23: =0 | D23: =C24*Supuestos!$D$8 | E23: =D24*Supuestos!$D$8 | F23: =E24*Supuestos!$D$8 | G23: =F24*Supuestos!$D$8 | H23: =G24*Supuestos!$D$8 | I23: =H24*Supuestos!$D$8 | J23: =I24*Supuestos!$D$8 | K23: =J24*Supuestos!$D$8 | ... AL23: =AK24*Supuestos!$D$8
A24: Clientes activos | C24: =C22 | D24: =C24+D22-D23 | E24: =D24+E22-E23 | F24: =E24+F22-F23 | G24: =F24+G22-G23 | H24: =G24+H22-H23 | I24: =H24+I22-I23 | J24: =I24+J22-J23 | K24: =J24+K22-K23 | ... AL24: =AK24+AL22-AL23
A25: Ingreso promedio por cliente (ARPU) | C25: =Supuestos!$D$9 | D25: =Supuestos!$D$9 | E25: =Supuestos!$D$9 | F25: =Supuestos!$D$9 | G25: =Supuestos!$D$9 | H25: =Supuestos!$D$9 | I25: =Supuestos!$D$9 | J25: =Supuestos!$D$9 | ... AL25: =Supuestos!$D$9
A26: Ingresos del mes | C26: =C24*C25 | D26: =D24*D25 | E26: =E24*E25 | F26: =F24*F25 | G26: =G24*G25 | H26: =H24*H25 | I26: =I24*I25 | J26: =J24*J25 | ... AL26: =AL24*AL25
A27: Costos variables | C27: =C24*Supuestos!$C$10+C26*Supuestos!$C$11 | D27: =D24*Supuestos!$C$10+D26*Supuestos!$C$11 | E27: =E24*Supuestos!$C$10+E26*Supuestos!$C$11 | F27: =F24*Supuestos!$C$10+F26*Supuestos!$C$11 | G27: =G24*Supuestos!$C$10+G26*Supuestos!$C$11 | H27: =H24*Supuestos!$C$10+H26*Supuestos!$C$11 | I27: =I24*Supuestos!$C$10+I26*Supuestos!$C$11 | J27: =J24*Supuestos!$C$10+J26*Supuestos!$C$11 | ... AL27: =AL24*Supuestos!$C$10+AL26*Supuestos!$C$11
A28: Costo de conseguir clientes | C28: =C22*Supuestos!$C$12 | D28: =D22*Supuestos!$C$12 | E28: =E22*Supuestos!$C$12 | F28: =F22*Supuestos!$C$12 | G28: =G22*Supuestos!$C$12 | H28: =H22*Supuestos!$C$12 | I28: =I22*Supuestos!$C$12 | J28: =J22*Supuestos!$C$12 | ... AL28: =AL22*Supuestos!$C$12
A29: Gastos fijos (equipo y operación) | C29: =SUMPRODUCT((Presupuesto!$D$5:$D$16<=C$4)*Presupuesto!$E$5:$E$16) | D29: =SUMPRODUCT((Presupuesto!$D$5:$D$16<=D$4)*Presupuesto!$E$5:$E$16) | E29: =SUMPRODUCT((Presupuesto!$D$5:$D$16<=E$4)*Presupuesto!$E$5:$E$16) | F29: =SUMPRODUCT((Presupuesto!$D$5:$D$16<=F$4)*Presupuesto!$E$5:$E$16) | G29: =SUMPRODUCT((Presupuesto!$D$5:$D$16<=G$4)*Presupuesto!$E$5:$E$16) | H29: =SUMPRODUCT((Presupuesto!$D$5:$D$16<=H$4)*Presupuesto!$E$5:$E$16) | I29: =SUMPRODUCT((Presupuesto!$D$5:$D$16<=I$4)*Presupuesto!$E$5:$E$16) | J29: =SUMPRODUCT((Presupuesto!$D$5:$D$16<=J$4)*Presupuesto!$E$5:$E$16) | ... AL29: =SUMPRODUCT((Presupuesto!$D$5:$D$16<=AL$4)*Presupuesto!$E$5:$E$16)
A30: Resultado operativo (EBITDA) | C30: =C26-C27-C28-C29 | D30: =D26-D27-D28-D29 | E30: =E26-E27-E28-E29 | F30: =F26-F27-F28-F29 | G30: =G26-G27-G28-G29 | H30: =H26-H27-H28-H29 | I30: =I26-I27-I28-I29 | J30: =J26-J27-J28-J29 | ... AL30: =AL26-AL27-AL28-AL29
A31: Caja acumulada (sin inversión) | C31: =C30-Presupuesto!$C$28 | D31: =C31+D30 | E31: =D31+E30 | F31: =E31+F30 | G31: =F31+G30 | H31: =G31+H30 | I31: =H31+I30 | J31: =I31+J30 | K31: =J31+K30 | ... AL31: =AK31+AL30
A32: ¿Mes con resultado positivo? (1 = sí) | C32: =IF(C30>0,1,0) | D32: =IF(D30>0,1,0) | E32: =IF(E30>0,1,0) | F32: =IF(F30>0,1,0) | G32: =IF(G30>0,1,0) | H32: =IF(H30>0,1,0) | I32: =IF(I30>0,1,0) | J32: =IF(J30>0,1,0) | ... AL32: =IF(AL30>0,1,0)
A35: Escenario Optimista
A36: Clientes nuevos | C36: =Supuestos!$E$6 | D36: =C36*(1+Supuestos!$E$7) | E36: =D36*(1+Supuestos!$E$7) | F36: =E36*(1+Supuestos!$E$7) | G36: =F36*(1+Supuestos!$E$7) | H36: =G36*(1+Supuestos!$E$7) | I36: =H36*(1+Supuestos!$E$7) | J36: =I36*(1+Supuestos!$E$7) | K36: =J36*(1+Supuestos!$E$7) | ... AL36: =AK36*(1+Supuestos!$E$7)
A37: Clientes que se van | C37: =0 | D37: =C38*Supuestos!$E$8 | E37: =D38*Supuestos!$E$8 | F37: =E38*Supuestos!$E$8 | G37: =F38*Supuestos!$E$8 | H37: =G38*Supuestos!$E$8 | I37: =H38*Supuestos!$E$8 | J37: =I38*Supuestos!$E$8 | K37: =J38*Supuestos!$E$8 | ... AL37: =AK38*Supuestos!$E$8
A38: Clientes activos | C38: =C36 | D38: =C38+D36-D37 | E38: =D38+E36-E37 | F38: =E38+F36-F37 | G38: =F38+G36-G37 | H38: =G38+H36-H37 | I38: =H38+I36-I37 | J38: =I38+J36-J37 | K38: =J38+K36-K37 | ... AL38: =AK38+AL36-AL37
A39: Ingreso promedio por cliente (ARPU) | C39: =Supuestos!$E$9 | D39: =Supuestos!$E$9 | E39: =Supuestos!$E$9 | F39: =Supuestos!$E$9 | G39: =Supuestos!$E$9 | H39: =Supuestos!$E$9 | I39: =Supuestos!$E$9 | J39: =Supuestos!$E$9 | ... AL39: =Supuestos!$E$9
A40: Ingresos del mes | C40: =C38*C39 | D40: =D38*D39 | E40: =E38*E39 | F40: =F38*F39 | G40: =G38*G39 | H40: =H38*H39 | I40: =I38*I39 | J40: =J38*J39 | ... AL40: =AL38*AL39
A41: Costos variables | C41: =C38*Supuestos!$C$10+C40*Supuestos!$C$11 | D41: =D38*Supuestos!$C$10+D40*Supuestos!$C$11 | E41: =E38*Supuestos!$C$10+E40*Supuestos!$C$11 | F41: =F38*Supuestos!$C$10+F40*Supuestos!$C$11 | G41: =G38*Supuestos!$C$10+G40*Supuestos!$C$11 | H41: =H38*Supuestos!$C$10+H40*Supuestos!$C$11 | I41: =I38*Supuestos!$C$10+I40*Supuestos!$C$11 | J41: =J38*Supuestos!$C$10+J40*Supuestos!$C$11 | ... AL41: =AL38*Supuestos!$C$10+AL40*Supuestos!$C$11
A42: Costo de conseguir clientes | C42: =C36*Supuestos!$C$12 | D42: =D36*Supuestos!$C$12 | E42: =E36*Supuestos!$C$12 | F42: =F36*Supuestos!$C$12 | G42: =G36*Supuestos!$C$12 | H42: =H36*Supuestos!$C$12 | I42: =I36*Supuestos!$C$12 | J42: =J36*Supuestos!$C$12 | ... AL42: =AL36*Supuestos!$C$12
A43: Gastos fijos (equipo y operación) | C43: =SUMPRODUCT((Presupuesto!$D$5:$D$16<=C$4)*Presupuesto!$E$5:$E$16) | D43: =SUMPRODUCT((Presupuesto!$D$5:$D$16<=D$4)*Presupuesto!$E$5:$E$16) | E43: =SUMPRODUCT((Presupuesto!$D$5:$D$16<=E$4)*Presupuesto!$E$5:$E$16) | F43: =SUMPRODUCT((Presupuesto!$D$5:$D$16<=F$4)*Presupuesto!$E$5:$E$16) | G43: =SUMPRODUCT((Presupuesto!$D$5:$D$16<=G$4)*Presupuesto!$E$5:$E$16) | H43: =SUMPRODUCT((Presupuesto!$D$5:$D$16<=H$4)*Presupuesto!$E$5:$E$16) | I43: =SUMPRODUCT((Presupuesto!$D$5:$D$16<=I$4)*Presupuesto!$E$5:$E$16) | J43: =SUMPRODUCT((Presupuesto!$D$5:$D$16<=J$4)*Presupuesto!$E$5:$E$16) | ... AL43: =SUMPRODUCT((Presupuesto!$D$5:$D$16<=AL$4)*Presupuesto!$E$5:$E$16)
A44: Resultado operativo (EBITDA) | C44: =C40-C41-C42-C43 | D44: =D40-D41-D42-D43 | E44: =E40-E41-E42-E43 | F44: =F40-F41-F42-F43 | G44: =G40-G41-G42-G43 | H44: =H40-H41-H42-H43 | I44: =I40-I41-I42-I43 | J44: =J40-J41-J42-J43 | ... AL44: =AL40-AL41-AL42-AL43
A45: Caja acumulada (sin inversión) | C45: =C44-Presupuesto!$C$28 | D45: =C45+D44 | E45: =D45+E44 | F45: =E45+F44 | G45: =F45+G44 | H45: =G45+H44 | I45: =H45+I44 | J45: =I45+J44 | K45: =J45+K44 | ... AL45: =AK45+AL44
A46: ¿Mes con resultado positivo? (1 = sí) | C46: =IF(C44>0,1,0) | D46: =IF(D44>0,1,0) | E46: =IF(E44>0,1,0) | F46: =IF(F44>0,1,0) | G46: =IF(G44>0,1,0) | H46: =IF(H44>0,1,0) | I46: =IF(I44>0,1,0) | J46: =IF(J44>0,1,0) | ... AL46: =IF(AL44>0,1,0)

Sheet Unidad económica
A1: Unidad económica (escenario base)
A2: Cuánto deja un cliente y cuánto cuesta conseguirlo
A4: Indicador | B4: Valor | C4: Cómo se calcula
A5: Ingreso promedio por cliente al mes (ARPU) | B5: =Supuestos!$D$9 | C5: Opción B, mezcla de planes
A6: Costo por cliente al mes | B6: =Supuestos!$C$10+B5*Supuestos!$C$11 | C6: Servidor, IA, soporte y comisión de cobro
A7: Margen bruto por cliente al mes | B7: =B5-B6 | C7: ARPU − costo
A8: Margen bruto % | B8: =IFERROR(B7/B5,0)
A9: Vida promedio del cliente (meses) | B9: =IFERROR(1/Supuestos!$D$8,0) | C9: 1 ÷ abandono mensual
A10: Valor de vida del cliente (LTV) | B10: =B7*B9 | C10: Margen × meses de vida
A11: Costo de conseguir un cliente (CAC) | B11: =Supuestos!$C$12 | C11: Supuesto
A12: LTV / CAC | B12: =IFERROR(B10/B11,0) | C12: Lo sano es 3x o más
A13: Meses para recuperar el CAC | B13: =IFERROR(B11/B7,0) | C13: CAC ÷ margen mensual

Sheet Uso de fondos
A1: Uso de fondos — tres tamaños de ronda
A2: Montos y porcentajes en azul: ajústalos según el inversionista
B4: Ángel (mínimo) | C4: Pre-semilla (recomendada) | D4: Semilla (acelerar) | E4: Nota
A5: Monto a levantar (US$) | B5: 100000 | C5: 350000 | D5: 700000
A6: Monto en COP | B6: =B5*Supuestos!$C$5 | C6: =C5*Supuestos!$C$5 | D6: =D5*Supuestos!$C$5
A8: Producto y tecnología (equipo de desarrollo, Play Store, nube) | B8: 0.5 | C8: 0.45 | D8: 0.4
A9: Ventas y marketing (vendedores de campo, pauta, referidos) | B9: 0.25 | C9: 0.3 | D9: 0.35
A10: Soporte y operación | B10: 0.1 | C10: 0.1 | D10: 0.1
A11: Legal, marca y factura electrónica DIAN | B11: 0.08 | C11: 0.07 | D11: 0.07
A12: Infraestructura y reserva | B12: 0.07 | C12: 0.08 | D12: 0.08
A13: Revisión: suma de porcentajes | B13: =SUM(B8:B12) | C13: =SUM(C8:C12) | D13: =SUM(D8:D12)
A15: En pesos
A16: =A8 | B16: =B$6*B8 | C16: =C$6*C8 | D16: =D$6*D8
A17: =A9 | B17: =B$6*B9 | C17: =C$6*C9 | D17: =D$6*D9
A18: =A10 | B18: =B$6*B10 | C18: =C$6*C10 | D18: =D$6*D10
A19: =A11 | B19: =B$6*B11 | C19: =C$6*C11 | D19: =D$6*D11
A20: =A12 | B20: =B$6*B12 | C20: =C$6*C12 | D20: =D$6*D12
A22: Meses de operación con todo el equipo (sin contar ventas) | B22: =IFERROR(B6/Presupuesto!$E$17,0) | C22: =IFERROR(C6/Presupuesto!$E$17,0) | D22: =IFERROR(D6/Presupuesto!$E$17,0)
A23: ¿Alcanza para el escenario base? (plata necesaria hasta el punto de equilibrio) | B23: =IF(B6>=Resumen!$C$16,"Sí","No: falta "&TEXT(Resumen!$C$16-B6,"$#,##0")) | C23: =IF(C6>=Resumen!$C$16,"Sí","No: falta "&TEXT(Resumen!$C$16-C6,"$#,##0")) | D23: =IF(D6>=Resumen!$C$16,"Sí","No: falta "&TEXT(Resumen!$C$16-D6,"$#,##0"))
A25: Contexto: en 2025 la inversión pre-semilla en Latinoamérica cayó cerca de 40 % (LAVCA); la mediana global de capital pre-semilla fue de unos US$0,8 millones en el segundo semestre de 2025 (Equidam).

Sheet Fuentes
A1: Fuentes
A3: Dato | B3: Enlace
A4: Micronegocios en Colombia (2.321.469, 24 ciudades, 2024) | B4: https://www.dane.gov.co/files/operaciones/EMICRON/bol-EMICRON-2024.pdf
A5: Bre-B: pagos inmediatos, 227 entidades, abierto desde el 6 oct 2025 | B5: https://banrep.gov.co/es/noticias/bre-b-semana-crece-expectativa-entrada-operacion-bre-b
A6: Nequi: más de 25 millones de usuarios (2025) | B6: https://www.elcolombiano.com/negocios/nequi-resumen-financiero-2025-como-mueven-plata-25-millones-usuarios-HH28857022
A7: Restaurantes: más de 150.000 establecimientos (Acodrés, dic. 2024) | B7: https://www.portafolio.co/negocios/empresas/acodres-afirma-que-el-ano-pasado-se-cerraron-casi-7-000-restaurantes-624468
A8: Bold: 230.000 comercios; datáfono 2,99 % por transacción; SonoQR | B8: https://www.larepublica.co/finanzas/la-fintech-bold-llego-a-230-000-comercios-y-anuncio-su-nuevo-proyecto-bold-smart-3430336
A9: Treinta: más de 5 millones de usuarios en 18 países, funciones gratis | B9: https://www.larepublica.co/finanzas/queremos-ser-la-super-app-de-referencia-para-los-micronegocios-de-america-latina-3404790
A10: Alegra Pyme $163.900/mes; Siigo Nube Emprendedor $191.327/mes | B10: https://blog.alegra.com/colombia/alegra-vs-siigo-colombia/
A11: Siigo POS Gastrobar desde $124.992/mes | B11: https://www.descubre.vc/noticia/siigo-lanza-pos-gastrobar-para-restaurantes-y-bares-en-colombia-2025-08-19
A12: Fudo: US$35–45/mes (planes internacionales) | B12: https://www.capterra.co.uk/software/1023879/fudo
A13: TRM 1 de octubre de 2026: $3.312,84 | B13: https://www.dolar-colombia.com/2026-10-01
A14: LAVCA Trends in Tech 2026 (caída de la pre-semilla en 2025) | B14: https://www.lavca.org/research/2026-lavca-trends-in-tech/
A15: Equidam: mediana global pre-semilla H2 2025 | B15: https://www.equidam.com/startup-valuation-delta-h2-2025/
